luaprot/__init__.py
luaprot/luaprot.py
luaprot-1.dist-info/METADATA
luaprot-1.dist-info/WHEEL
luaprot-1.dist-info/top_level.txt
luaprot-1.dist-info/RECORD
