Metadata-Version: 2.1
Name: luaprot
Version: 1
Summary: The offical python package for the LuaProt whitelisting service
Author: luaprot
Author-email: protlua@gmail.com
